pyplanner/__init__.py
pyplanner/__main__.py
pyplanner/_global.py
pyplanner/cron_job.py
pyplanner/db_ops.py
pyplanner/os_checker.py
pyplanner/task_list.py
pyplanner-0.0.1.dist-info/LICENSE
pyplanner-0.0.1.dist-info/METADATA
pyplanner-0.0.1.dist-info/WHEEL
pyplanner-0.0.1.dist-info/top_level.txt
pyplanner-0.0.1.dist-info/RECORD
