Metadata-Version: 2.1
Name: pyplanner
Version: 0.0.1
Summary: pyplanner keeps track of all your activities and notifies you when they are due
Home-page: https://github.com/subhendudash02/pyplanner
Author: Subhendu Dash
Author-email: sdash29102@gmail.com
Classifier: Programming Language :: Python :: 3
Classifier: License :: OSI Approved :: MIT License
Classifier: Operating System :: POSIX :: Linux
Requires-Python: >=3.8
License-File: LICENSE
